multiriver/__init__.py
multiriver/azure_blob_session.py
multiriver/bson_utils.py
multiriver/click_utils.py
multiriver/main.py
multiriver/rivery_session.py
multiriver/utils.py
multiriver-1.1.15.dist-info/METADATA
multiriver-1.1.15.dist-info/WHEEL
multiriver-1.1.15.dist-info/entry_points.txt
multiriver-1.1.15.dist-info/top_level.txt
multiriver-1.1.15.dist-info/RECORD
