Metadata-Version: 2.1
Name: multiriver
Version: 1.1.15
Summary: A tool for bulk river creation
Author: Oleksandr Baranov
Author-email: oleksandr.baranov@rivery.io
Classifier: Programming Language :: Python :: 3
Classifier: License :: OSI Approved :: MIT License
Classifier: Operating System :: OS Independent
Requires-Python: >=3.6
Requires-Dist: azure-storage-blob (==12.23.1)
Requires-Dist: azure.identity (==1.19.0)
Requires-Dist: click (==7.1.2)
Requires-Dist: pymongo (==3.13.0)
Requires-Dist: Requests (==2.32.3)
Requires-Dist: rich (==13.9.4)
Requires-Dist: simplejson (==3.19.2)
